robotoy/__init__.py
robotoy/container/ring_buffer.cpython-39-darwin.so
robotoy/counter/__init__.py
robotoy/fast/__init__.py
robotoy/fast/plane.py
robotoy/itp_state/1.py
robotoy/itp_state/__init__.py
robotoy/itp_state/api.py
robotoy/itp_state/itp_state.cpython-39-darwin.so
robotoy/itp_state/itp_state_py.py
robotoy/itp_state/show.py
robotoy/itp_state/test.py
robotoy/itp_state/test2.py
robotoy/itp_state/test_file.py
robotoy/itp_state/test_itp_q.py
robotoy/kalman/__init__.py
robotoy/kalman/linear_kalman.py
robotoy/kin/__init__.py
robotoy/kin/scipy_ik_solver.py
robotoy/pipe/__init__.py
robotoy/time_utils/__init__.py
robotoy-0.2.dist-info/METADATA
robotoy-0.2.dist-info/WHEEL
robotoy-0.2.dist-info/top_level.txt
robotoy-0.2.dist-info/RECORD
