Metadata-Version: 2.1
Name: robotoy
Version: 0.2
Summary: A package for fast mathematical computations using C++ extensions.
Home-page: UNKNOWN
License: UNKNOWN
Platform: UNKNOWN
